mend_circleci_python_library/__init__.py
mend_circleci_python_library/generator.py
mend_circleci_python_library/templates/_circleci.jinja
mend_circleci_python_library/templates/.circleci/config.yml
mend_circleci_python_library-0.2.0.dist-info/LICENSE
mend_circleci_python_library-0.2.0.dist-info/METADATA
mend_circleci_python_library-0.2.0.dist-info/WHEEL
mend_circleci_python_library-0.2.0.dist-info/entry_points.txt
mend_circleci_python_library-0.2.0.dist-info/top_level.txt
mend_circleci_python_library-0.2.0.dist-info/RECORD
